Metadata-Version: 2.1
Name: pepsi
Version: 0.1.3
Summary: Simple module to color all your text in a certain way
Home-page: https://github.com/JustAProDev
Author: Yurei
Author-email: unknownrussian100@gmail.com
License: MIT
Project-URL: GitHub, https://github.com/0xPacker/
Keywords: discord
Classifier: Programming Language :: Python :: 3
Classifier: License :: OSI Approved :: MIT License
Classifier: Operating System :: Microsoft :: Windows
Classifier: Development Status :: 5 - Production/Stable
Classifier: Intended Audience :: Developers
Classifier: Natural Language :: English
Classifier: Topic :: Software Development
